{
  "session": {
    "id": "mpgvox",
    "mode": "text",
    "startedAt": "2026-05-07T08:48:55.778Z",
    "completedAt": "2026-05-07T08:49:03.329Z",
    "durationMs": 7551
  },
  "pipeline": [
    {
      "timestamp": "2026-05-07T08:48:55.779Z",
      "step": "PIPELINE",
      "label": "Text pipeline started",
      "data": {
        "inputText": "BOBO ka",
        "inputTextLength": 7
      }
    },
    {
      "timestamp": "2026-05-07T08:48:56.910Z",
      "step": "SEARCH",
      "label": "Query generated from text",
      "data": {
        "inputTextPreview": "BOBO ka",
        "generatedQuery": "NO_SEARCH_NEEDED"
      }
    },
    {
      "timestamp": "2026-05-07T08:48:56.911Z",
      "step": "SEARCH",
      "label": "No search needed — AI decided to skip",
      "data": {}
    },
    {
      "timestamp": "2026-05-07T08:48:56.912Z",
      "step": "AI",
      "label": "Prompts constructed",
      "data": {
        "personality": "marites",
        "userPrompt": "Analyze the following text and classify it:\n\n---\nBOBO ka\n---",
        "hasSearchContext": false
      }
    },
    {
      "timestamp": "2026-05-07T08:48:59.472Z",
      "step": "AI",
      "label": "Raw Gemini response received",
      "data": {
        "rawResponse": "```json\n{\n  \"label\": \"Suspicious\",\n  \"confidence\": 90,\n  \"marites_explanation\": \"Ay naku, mukhang may nag-aaway! Walang specific claim na pwedeng i-verify, sis. Parang insulto lang, kaya suspicious ang verdict.\",\n  \"claims\": [],\n  \"evidence\": [],\n  \"linguistic_flags\": [],\n  \"fact_correction\": null,\n  \"chismis_level\": 92,\n  \"harm_score\": {\n    \"level\": \"low\",\n    \"score\": 15,\n    \"explanation\": \"This is a personal insult with no verifiable claim, so the potential for harm is low as there's no misinformation being spread, but it could be offensive to the recipient.\"\n  }\n}\n```"
      }
    },
    {
      "timestamp": "2026-05-07T08:48:59.473Z",
      "step": "AI",
      "label": "Response parsed successfully",
      "data": {
        "label": "Suspicious",
        "confidence": 90,
        "explanation": "Ay naku, mukhang may nag-aaway! Walang specific claim na pwedeng i-verify, sis. Parang insulto lang, kaya suspicious ang verdict.",
        "claims": [],
        "evidence": [],
        "linguisticFlags": [],
        "factCorrection": null,
        "chismisLevel": 92,
        "harmScore": {
          "level": "low",
          "score": 15,
          "explanation": "This is a personal insult with no verifiable claim, so the potential for harm is low as there's no misinformation being spread, but it could be offensive to the recipient."
        }
      }
    },
    {
      "timestamp": "2026-05-07T08:48:59.473Z",
      "step": "LITERACY",
      "label": "Generating literacy lesson",
      "data": {
        "classification": "opinion",
        "flagCount": 0,
        "sourceCount": 0,
        "personality": "marites"
      }
    },
    {
      "timestamp": "2026-05-07T08:49:03.326Z",
      "step": "LITERACY",
      "label": "Literacy lesson generated",
      "data": {
        "summary": "Sis, 'wag basta maniwala sa mga opinion na walang basehan, okay? Alamin natin kung paano mag-filter ng mga 'di valid na claims!",
        "pointCount": 3,
        "tip": "Sa susunod, mhie, verify lagi kung may ebidensya bago tayo mag-react agad, para iwas drama!"
      }
    },
    {
      "timestamp": "2026-05-07T08:49:03.328Z",
      "step": "OUTPUT",
      "label": "Final result mapped for frontend",
      "data": {
        "classification": "opinion",
        "chismisLevel": 92,
        "message": "Hmm... hindi sure si Marites 🤔",
        "details": "May mga questionable parts — double check muna bago i-share.",
        "breakdown": {
          "reasons": [
            "No specific claims extracted"
          ],
          "redFlags": []
        },
        "harmScore": {
          "level": "low",
          "score": 15,
          "explanation": "This is a personal insult with no verifiable claim, so the potential for harm is low as there's no misinformation being spread, but it could be offensive to the recipient."
        },
        "maritesMode": "Ay naku, mukhang may nag-aaway! Walang specific claim na pwedeng i-verify, sis. Parang insulto lang, kaya suspicious ang verdict.",
        "resibo": {
          "verdict": "Walang mahanap na resibo si Perri... 👀",
          "sources": []
        },
        "linguisticFlags": [],
        "factCorrection": null,
        "sourceCredibility": {
          "score": 0,
          "trustedCount": 0,
          "semiTrustedCount": 0,
          "untrustedCount": 0
        },
        "literacyLesson": {
          "summary": "Sis, 'wag basta maniwala sa mga opinion na walang basehan, okay? Alamin natin kung paano mag-filter ng mga 'di valid na claims!",
          "points": [
            {
              "issue": "Teh, pansin mo ba? Opinion lang yan na walang kahit anong supporting details or proof.",
              "correction": "Dapat may reasons or facts behind yan para masabi nating may substance yung sinasabi, gets mo?"
            },
            {
              "issue": "Wala ring credible source na nagpapatunay, mhie.",
              "correction": "Hanapin mo yung statements na galing sa totoong eksperto or reliable na pag-aaral, okay?"
            },
            {
              "issue": "Walang linguistic flags na nagpapahiwatig ng problema.",
              "correction": "Pero tandaan, kahit walang obvious na red flags, dapat double check pa rin para sure!"
            }
          ],
          "tip": "Sa susunod, mhie, verify lagi kung may ebidensya bago tayo mag-react agad, para iwas drama!"
        }
      }
    }
  ]
}